flatten_anything/__init__.py
flatten_anything/flatten.py
flatten_anything/ingest.py
flatten_anything/utils.py
flatten_anything/formats/__init__.py
flatten_anything/formats/api.py
flatten_anything/formats/csv.py
flatten_anything/formats/excel.py
flatten_anything/formats/json.py
flatten_anything/formats/parquet.py
flatten_anything/formats/xml.py
flatten_anything/formats/yaml.py
flatten_anything/tests/__init__.py
flatten_anything/tests/test_basic_functionality.py
flatten_anything/tests/test_complex_structures.py
flatten_anything/tests/test_v1_1_functionality.py
flatten_anything/tests/test_v1_1_streaming.py
flatten_anything-1.1.1.dist-info/licenses/LICENSE
flatten_anything-1.1.1.dist-info/METADATA
flatten_anything-1.1.1.dist-info/WHEEL
flatten_anything-1.1.1.dist-info/top_level.txt
flatten_anything-1.1.1.dist-info/RECORD
