Metadata-Version: 2.4
Name: flatten-anything
Version: 1.1.1
Summary: Stop writing custom parsers for every data format. Flatten anything.
Home-page: https://github.com/BudLight-Year/flatten-anything
Author: Evan Cline
Author-email: totallysweethobo@gmail.com
Project-URL: Bug Reports, https://github.com/BudLight-Year/flatten-anything/issues
Project-URL: Source, https://github.com/BudLight-Year/flatten-anything
Project-URL: Documentation, https://github.com/BudLight-Year/flatten-anything#readme
Keywords: flatten json csv parquet excel yaml xml data transformation etl ingest ingestion dot-notation
Classifier: Development Status :: 5 - Production/Stable
Classifier: Intended Audience :: Developers
Classifier: Topic :: Software Development :: Libraries :: Python Modules
Classifier: Topic :: Utilities
Classifier: License :: OSI Approved :: MIT License
Classifier: Programming Language :: Python :: 3
Classifier: Programming Language :: Python :: 3.8
Classifier: Programming Language :: Python :: 3.9
Classifier: Programming Language :: Python :: 3.10
Classifier: Programming Language :: Python :: 3.11
Classifier: Programming Language :: Python :: 3.12
Classifier: Operating System :: OS Independent
Requires-Python: >=3.8
License-File: LICENSE
Requires-Dist: pandas>=1.0.0
Requires-Dist: pyyaml>=5.3
Requires-Dist: xmltodict>=0.12.0
Requires-Dist: requests>=2.20.0
Provides-Extra: parquet
Requires-Dist: pyarrow>=4.0.0; extra == "parquet"
Provides-Extra: excel
Requires-Dist: openpyxl>=3.0.0; extra == "excel"
Provides-Extra: all
Requires-Dist: pyarrow>=4.0.0; extra == "all"
Requires-Dist: openpyxl>=3.0.0; extra == "all"
Provides-Extra: dev
Requires-Dist: pytest>=6.0.0; extra == "dev"
Requires-Dist: pytest-cov>=2.10.0; extra == "dev"
Requires-Dist: black>=21.0; extra == "dev"
Requires-Dist: flake8>=3.9.0; extra == "dev"
Dynamic: author
Dynamic: author-email
Dynamic: classifier
Dynamic: description
Dynamic: description-content-type
Dynamic: home-page
Dynamic: keywords
Dynamic: license-file
Dynamic: project-url
Dynamic: provides-extra
Dynamic: requires-dist
Dynamic: requires-python
Dynamic: summary
